brave_api/__init__.py
brave_api/client.py
brave_api/constants.py
brave_api/web_search/__init__.py
brave_api/web_search/models.py
brave_api_client-0.0.4.dist-info/METADATA
brave_api_client-0.0.4.dist-info/WHEEL
brave_api_client-0.0.4.dist-info/licenses/LICENSE
brave_api_client-0.0.4.dist-info/RECORD
