Metadata-Version: 2.4
Name: brave-api-client
Version: 0.0.4
Summary: Brave API client for Python
License-File: LICENSE
Classifier: Programming Language :: Python :: 3.10
Classifier: Programming Language :: Python :: 3.11
Classifier: Programming Language :: Python :: 3.12
Classifier: Programming Language :: Python :: 3.13
Classifier: Typing :: Typed
Requires-Python: <4,>=3.10
Requires-Dist: httpx>=0.28.1
Requires-Dist: pydantic>=2.11.5
